thematicnifty/__init__.py
thematicnifty/tn.py
thematicnifty-0.1.4.dist-info/METADATA
thematicnifty-0.1.4.dist-info/WHEEL
thematicnifty-0.1.4.dist-info/top_level.txt
thematicnifty-0.1.4.dist-info/RECORD
