Metadata-Version: 2.1
Name: thematicnifty
Version: 0.1.4
Summary: A small package that helps you in fetching list of stocks from National Stock Exchange (NSE) based on main_item, sub_item values and returnOutput.
Author: Dr. Kumar B V
Author-email: kumar.bv@gmail.com
License: UNKNOWN
Platform: UNKNOWN
Classifier: Programming Language :: Python :: 3
Classifier: License :: OSI Approved :: MIT License
Classifier: Operating System :: OS Independent
Requires-Python: >=3.7
